forofo/__init__.py
forofo/scripts.py
forofo/utils.py
forofo/datagokr/__init__.py
forofo/datagokr/client.py
forofo/datagokr/common.py
forofo/datagokr/exceptions.py
forofo/datagokr/airkorea/ArpltnInforInqireSvc.py
forofo/datagokr/airkorea/__init__.py
forofo/datagokr/elevator/ElevatorAcdnService.py
forofo/datagokr/elevator/ElevatorInstallationService.py
forofo/datagokr/elevator/__init__.py
forofo/datagokr/kma/AsosHourlyInfoService.py
forofo/datagokr/kma/MidFcstInfoService.py
forofo/datagokr/kma/VilageFcstInfoService_2_0.py
forofo/datagokr/kma/__init__.py
forofo/datagokr/kma/info.py
forofo/datagokr/kpx/__init__.py
forofo/datagokr/kpx/kpx.py
forofo/datagokr/molit/RTMSOBJSvc.py
forofo/datagokr/molit/__init__.py
forofo/kma_url_api/__init__.py
forofo/kma_url_api/client.py
forofo/kma_url_api/common.py
forofo/kma_url_api/exceptions.py
forofo/kma_url_api/models.py
forofo/kma_url_api/parser.py
forofo/localdata/__init__.py
forofo/localdata/client.py
forofo/localdata/common.py
forofo/localdata/exceptions.py
forofo-2022.9.2.dist-info/METADATA
forofo-2022.9.2.dist-info/WHEEL
forofo-2022.9.2.dist-info/dependency_links.txt
forofo-2022.9.2.dist-info/entry_points.txt
forofo-2022.9.2.dist-info/top_level.txt
forofo-2022.9.2.dist-info/RECORD
