Metadata-Version: 2.1
Name: forofo
Version: 2022.9.2
Author: Woojin Cho
Author-email: woojin.cho@gsenc.com
License: GS E&C Internal Only
Requires-Python: >=3.8
Requires-Dist: aiohttp
Requires-Dist: click
Requires-Dist: click-loglevel
Requires-Dist: clutter
Requires-Dist: croniter
Requires-Dist: fastapi
Requires-Dist: fastnumbers
Requires-Dist: loguru
Requires-Dist: parse
Requires-Dist: pendulum
Requires-Dist: pydantic
Requires-Dist: pytest
Requires-Dist: xmltodict
